npktest.py
setup.py
npk/__init__.py
npk/_cffi.py
npk/entity.py
npk/error.py
npk/package.py
pynpk.egg-info/PKG-INFO
pynpk.egg-info/SOURCES.txt
pynpk.egg-info/dependency_links.txt
pynpk.egg-info/requires.txt
pynpk.egg-info/top_level.txt
testres/sample.npk
testres/sample.txt