Metadata-Version: 1.0
Name: pynpk
Version: 0.1.1
Summary: pynpk
Home-page: http://github.com/lqez/pynpk
Author: Park Hyunwoo
Author-email: ez.amiryo@gmail.com
License: UNKNOWN
Platform: UNKNOWN
Classifier: Development Status :: 3 - Alpha
Classifier: Intended Audience :: Developers
Classifier: Intended Audience :: System Administrators
Classifier: Programming Language :: Python
Classifier: Programming Language :: Python :: 2.7
Classifier: License :: OSI Approved :: MIT License
